rocketgram-6.0.4.dist-info/METADATA
rocketgram-6.0.4.dist-info/WHEEL
rocketgram-6.0.4.dist-info/licenses/LICENSE
rocketgram/__init__.py
rocketgram/api/__init__.py
rocketgram/api/add_sticker_to_set.py
rocketgram/api/animation.py
rocketgram/api/answer_callback_query.py
rocketgram/api/answer_inline_query.py
rocketgram/api/answer_pre_checkout_query.py
rocketgram/api/answer_shipping_query.py
rocketgram/api/answer_web_app_query.py
rocketgram/api/approve_chat_join_request.py
rocketgram/api/audio.py
rocketgram/api/ban_chat_member.py
rocketgram/api/ban_chat_sender_chat.py
rocketgram/api/bot_command.py
rocketgram/api/bot_command_scope.py
rocketgram/api/bot_command_scope_all_chat_administrators.py
rocketgram/api/bot_command_scope_all_group_chats.py
rocketgram/api/bot_command_scope_all_private_chats.py
rocketgram/api/bot_command_scope_chat.py
rocketgram/api/bot_command_scope_chat_administrators.py
rocketgram/api/bot_command_scope_chat_member.py
rocketgram/api/bot_command_scope_default.py
rocketgram/api/bot_description.py
rocketgram/api/bot_name.py
rocketgram/api/bot_short_description.py
rocketgram/api/callback_query.py
rocketgram/api/chat.py
rocketgram/api/chat_action_type.py
rocketgram/api/chat_administrator_rights.py
rocketgram/api/chat_boost.py
rocketgram/api/chat_boost_added.py
rocketgram/api/chat_boost_removed.py
rocketgram/api/chat_boost_source.py
rocketgram/api/chat_boost_source_type.py
rocketgram/api/chat_boost_updated.py
rocketgram/api/chat_invite_link.py
rocketgram/api/chat_join_request.py
rocketgram/api/chat_location.py
rocketgram/api/chat_member.py
rocketgram/api/chat_member_status_type.py
rocketgram/api/chat_member_updated.py
rocketgram/api/chat_permissions.py
rocketgram/api/chat_photo.py
rocketgram/api/chat_shared.py
rocketgram/api/chat_type.py
rocketgram/api/chosen_inline_result.py
rocketgram/api/close.py
rocketgram/api/close_forum_topic.py
rocketgram/api/close_general_forum_topic.py
rocketgram/api/contact.py
rocketgram/api/copy_message.py
rocketgram/api/copy_messages.py
rocketgram/api/create_chat_invite_link.py
rocketgram/api/create_forum_topic.py
rocketgram-6.0.4.dist-info/RECORD
