Metadata-Version: 2.1
Name: rocketgram
Version: 6.0.4
Summary: Modern and powerful asynchronous telegram bot framework.
Keywords: telegram bot framework rocketgram async asyncio rocket
Home-page: https://github.com/vd2org/wultiplexor
Author-Email: Vd <rocketgram@vd2.org>
License: Copyright 2015-2024 Vd
Classifier: Development Status :: 5 - Production/Stable
Classifier: Framework :: AsyncIO
Classifier: Intended Audience :: Developers
Classifier: Intended Audience :: Education
Classifier: Intended Audience :: Information Technology
Classifier: License :: OSI Approved :: MIT License
Classifier: Natural Language :: English
Classifier: Operating System :: OS Independent
Classifier: Environment :: Web Environment
Classifier: Programming Language :: Python :: 3.12
Classifier: Programming Language :: Python :: 3.11
Classifier: Programming Language :: Python :: 3.10
Classifier: Programming Language :: Python :: 3.9
Classifier: Programming Language :: Python :: 3.8
Classifier: Programming Language :: Python :: 3.7
Classifier: Programming Language :: Python :: 3 :: Only
Classifier: Topic :: Communications :: Chat
Classifier: Topic :: Internet
Classifier: Topic :: Utilities
Classifier: Topic :: Software Development
Classifier: Topic :: Software Development :: Libraries
Classifier: Topic :: Software Development :: Libraries :: Application Frameworks
Classifier: Topic :: Software Development :: Libraries :: Python Modules
Project-URL: Homepage, https://github.com/vd2org/wultiplexor
Project-URL: Repository, https://github.com/vd2org/wultiplexor.git
Project-URL: Issues, https://github.com/vd2org/wultiplexor/issues
Requires-Python: <3.13,>=3.8
Provides-Extra: aiohttp
Provides-Extra: ujson
Provides-Extra: orjson
Requires-Dist: aiohttp~=3.9.3; extra == "aiohttp"
Requires-Dist: ujson~=5.9.0; extra == "ujson"
Requires-Dist: orjson~=3.9.15; extra == "orjson"
